rdfox_runner/__init__.py
rdfox_runner/command_runner.py
rdfox_runner/rdfox_endpoint.py
rdfox_runner/run_rdfox.py
rdfox_runner-0.6.2.dist-info/LICENSE
rdfox_runner-0.6.2.dist-info/METADATA
rdfox_runner-0.6.2.dist-info/WHEEL
rdfox_runner-0.6.2.dist-info/RECORD
