Metadata-Version: 2.1
Name: rdfox_runner
Version: 0.6.2
Summary: 
Author: Rick Lupton
Author-email: mail@ricklupton.name
Requires-Python: >=3.7,<4.0
Classifier: Programming Language :: Python :: 3
Classifier: Programming Language :: Python :: 3.7
Classifier: Programming Language :: Python :: 3.8
Classifier: Programming Language :: Python :: 3.9
Classifier: Programming Language :: Python :: 3.10
Classifier: Programming Language :: Python :: 3.11
Classifier: Programming Language :: Python :: 3.12
Requires-Dist: importlib-metadata (>=1.0) ; python_version < "3.8"
Requires-Dist: packaging (>=15.0)
Requires-Dist: rdflib (>=6.0.0,<7.0.0)
Requires-Dist: requests (>=2.25.1,<3.0.0)
